fake/__init__.py
fake/createproduct.py
fake/data.py
fake/get.py
fakeapistories/__init__.py
fakeapistories/createproduct.py
fakeapistories/data.py
fakeapistories/get.py
fakeapistories-0.1.dist-info/LICENSE.txt
fakeapistories-0.1.dist-info/METADATA
fakeapistories-0.1.dist-info/WHEEL
fakeapistories-0.1.dist-info/top_level.txt
fakeapistories-0.1.dist-info/RECORD
